[
  {
    "author": {
      "id": "m.juand18@gmail.com",
      "nombre": "asd",
      "apellido": "",
      "edad": "123",
      "alias": "123",
      "avatar": "1231"
    },
    "timestamp": "26-11-2022, 21:53:30",
    "message": "Primero"
  },
  {
    "author": {
      "id": "m.juand18@gmail.com",
      "nombre": "Pedro",
      "apellido": "calma",
      "edad": "23",
      "alias": "asd",
      "avatar": "asd"
    },
    "timestamp": "26-11-2022, 21:56:57",
    "message": "asd"
  },
  {
    "author": {
      "id": "m.juand18@gmail.com",
      "nombre": "Paco",
      "apellido": "Luna",
      "edad": "13",
      "alias": "lala",
      "avatar": "pasd"
    },
    "timestamp": "26-11-2022, 22:08:30",
    "message": "lala"
  },
  {
    "author": {
      "id": "laura@gmail.com",
      "nombre": "Laura",
      "apellido": "Ferrer",
      "edad": "25",
      "alias": "lola",
      "avatar": "lasd"
    },
    "timestamp": "26-11-2022, 23:25:02",
    "message": "Que tal"
  }
]